{
        "0":  {
                "OGC_doc_number": "21-998",
                "urn":"http://www.opengis.net/doc/EG/GeoPose-Reviewers-Guide/1.0",
                "title":"OGC GeoPose Reviewers Guide",
                "path":"reviewers_guide/GeoPose-Reviewers-Guide.adoc",
                "options": ["--trace"],
                "a":[
                        "data-uri",
                        "stylesdir=./resources/stylesheets",
                        "dot=/usr/bin/dot"
                ],
                "r":[
                        "asciidoctor-diagram"
                ]
        },
        "1":  {
                "OGC_doc_number": "21-999",
                "urn":"http://www.opengis.net/doc/EG/GeoPose-Users-Guide/1.0",
                "title":"OGC GeoPose Users Guide",
                "path":"users_guide/GeoPose-Users-Guide.adoc",
                "options": ["--trace"],
                "a":[
                        "data-uri",
                        "stylesdir=./resources/stylesheets",
                        "dot=/usr/bin/dot"
                ],
                "r":[
                        "asciidoctor-diagram"
                ]
        }
}
